setup.py
cybersecurity/__init__.py
cybersecurity/collection.py
cybersecurity/mytest.py
cybersecurity.egg-info/PKG-INFO
cybersecurity.egg-info/SOURCES.txt
cybersecurity.egg-info/dependency_links.txt
cybersecurity.egg-info/not-zip-safe
cybersecurity.egg-info/top_level.txt
cybersecurity/other/__init__.py
cybersecurity/other/mytest.py