Metadata-Version: 1.0
Name: cybersecurity
Version: 0.11
Summary: cybersecurity module
Home-page: http://github.com/cmhung/cybersecurity
Author: Hung
Author-email: cmhung@mail.ksu.edu.tw
License: MIT
Platform: UNKNOWN
